fc_dc_bigdata.py
fc_penwei250-1.0.dist-info/METADATA
fc_penwei250-1.0.dist-info/WHEEL
fc_penwei250-1.0.dist-info/top_level.txt
fc_penwei250-1.0.dist-info/RECORD
